odoo/addons/shopinvader_fastapi_auth_jwt/README.rst
odoo/addons/shopinvader_fastapi_auth_jwt/__init__.py
odoo/addons/shopinvader_fastapi_auth_jwt/__manifest__.py
odoo/addons/shopinvader_fastapi_auth_jwt/dependencies.py
odoo/addons/shopinvader_fastapi_auth_jwt/i18n/shopinvader_fastapi_auth_jwt.pot
odoo/addons/shopinvader_fastapi_auth_jwt/readme/DESCRIPTION.rst
odoo/addons/shopinvader_fastapi_auth_jwt/readme/USAGE.rst
odoo/addons/shopinvader_fastapi_auth_jwt/static/description/index.html
odoo/addons/shopinvader_fastapi_auth_jwt/tests/__init__.py
odoo/addons/shopinvader_fastapi_auth_jwt/tests/test_auth_jwt_or_anonymous.py
odoo_addon_shopinvader_fastapi_auth_jwt-16.0.1.0.3.dist-info/METADATA
odoo_addon_shopinvader_fastapi_auth_jwt-16.0.1.0.3.dist-info/WHEEL
odoo_addon_shopinvader_fastapi_auth_jwt-16.0.1.0.3.dist-info/top_level.txt
odoo_addon_shopinvader_fastapi_auth_jwt-16.0.1.0.3.dist-info/RECORD
