Metadata-Version: 2.1
Name: odoo-addon-shopinvader_fastapi_auth_jwt
Version: 16.0.1.0.3
Summary: Provide JWT and Anonymous Partner authentication to FastAPI routes.
Home-page: https://github.com/shopinvader/odoo-shopinvader
Author: ACSONE SA/NV
License: LGPL-3
Classifier: Programming Language :: Python
Classifier: Framework :: Odoo
Classifier: Framework :: Odoo :: 16.0
Classifier: License :: OSI Approved :: GNU Lesser General Public License v3 (LGPLv3)
Requires-Python: >=3.10
Requires-Dist: odoo-addon-fastapi-auth-jwt<16.1dev,>=16.0dev
Requires-Dist: odoo-addon-shopinvader-anonymous-partner<16.1dev,>=16.0dev
Requires-Dist: odoo<16.1dev,>=16.0a
